Metadata-Version: 2.1
Name: ultralytics-yolov5
Version: 0.1.0
Summary: UNKNOWN
Home-page: https://github.com/ultralytics/yolov5
Author: Ultralytics
Author-email: hello@ultralytics.com
License: Apache
Platform: UNKNOWN
Classifier: Intended Audience :: Science/Research
Classifier: Development Status :: 3 - Alpha
Classifier: License :: OSI Approved :: Apache Software License
Classifier: Programming Language :: Python :: 3
Classifier: Topic :: Scientific/Engineering :: Artificial Intelligence
Requires-Python: >=3.7
Provides-Extra: dev
License-File: LICENSE
